django_rubble/__init__.py
django_rubble/admin/__init__.py
django_rubble/admin/number_admin.py
django_rubble/admin/stamped_admin.py
django_rubble/apps.py
django_rubble/checks/__init__.py
django_rubble/checks/messages.py
django_rubble/context/__init__.py
django_rubble/context/sites.py
django_rubble/fields/__init__.py
django_rubble/fields/auto_fields.py
django_rubble/fields/db_fields.py
django_rubble/fields/test_db_fields.py
django_rubble/fields/test_fields.py
django_rubble/forms/__init__.py
django_rubble/forms/db_forms.py
django_rubble/migrations/0001_initial.py
django_rubble/migrations/__init__.py
django_rubble/models/__init__.py
django_rubble/models/factories.py
django_rubble/models/history_models.py
django_rubble/models/number_models.py
django_rubble/models/stamped_models.py
django_rubble/utils/__init__.py
django_rubble/utils/default_funcs.py
django_rubble/utils/enums.py
django_rubble/utils/model_helpers.py
django_rubble/utils/numbers.py
django_rubble/utils/strings.py
django_rubble/utils/test_numbers.py
django_rubble/views/__init__.py
django_rubble/views/create_views.py
django_rubble/widgets.py
django_rubble-0.6.0.dist-info/LICENSE
django_rubble-0.6.0.dist-info/METADATA
django_rubble-0.6.0.dist-info/WHEEL
django_rubble-0.6.0.dist-info/RECORD
