Metadata-Version: 2.1
Name: django-rubble
Version: 0.6.0
Summary: Extend django-model-utils and django-extensions.
Home-page: https://github.com/WoosterTech/django-rubble
License: MIT
Keywords: django,django-model-utils,django-extensions
Author: Karl Wooster
Author-email: karl@woostertech.com
Requires-Python: >=3.10,<4.0
Classifier: Framework :: Django :: 4
Classifier: Framework :: Django :: 4.0
Classifier: Framework :: Django :: 4.1
Classifier: Framework :: Django :: 4.2
Classifier: Framework :: Django :: 5.0
Classifier: Framework :: Django :: 5.1
Classifier: License :: OSI Approved :: MIT License
Classifier: Programming Language :: Python :: 3
Classifier: Programming Language :: Python :: 3.10
Classifier: Programming Language :: Python :: 3.11
Classifier: Programming Language :: Python :: 3.12
Provides-Extra: all
Provides-Extra: history
Provides-Extra: project
Requires-Dist: croniter (>=3.0.3,<4.0.0)
Requires-Dist: django (>4,<5.3)
Requires-Dist: django-model-utils (>=4.5.1,<5.0.0)
Requires-Dist: django-simple-history (>=3.7.0,<4.0.0) ; extra == "history" or extra == "all"
Requires-Dist: loguru (>=0.7.2,<0.8.0)
Requires-Dist: neapolitan (>=24.6,<25.0) ; extra == "project" or extra == "all"
Requires-Dist: pydantic (>=2.6.4,<3.0.0)
Project-URL: Bug Tracker, https://github.com/WoosterTech/django-rubble/issues
Project-URL: Change Log, https://github.com/WoosterTech/django-rubble/blob/main/CHANGELOG.md
Project-URL: Documentation, https://woostertech.github.io/django-rubble/
Project-URL: Repository, https://github.com/WoosterTech/django-rubble
